generic_encryptors/__init__.py
generic_encryptors/encryptors/__init__.py
generic_encryptors/encryptors/aes_encryptor.py
generic_encryptors/encryptors/exceptions.py
generic_encryptors-1.0.2.data/data/LICENSE
generic_encryptors-1.0.2.data/data/VERSION
generic_encryptors-1.0.2.dist-info/LICENSE
generic_encryptors-1.0.2.dist-info/METADATA
generic_encryptors-1.0.2.dist-info/WHEEL
generic_encryptors-1.0.2.dist-info/top_level.txt
generic_encryptors-1.0.2.dist-info/RECORD
