Metadata-Version: 2.1
Name: generic-encryptors
Version: 1.0.2
Summary:   A set of encryptors which provide an interface compatible with https://github.com/mmontagna/generic-encoders
Home-page: https://github.com/mmontagna/generic-encryptors
Author: Marco Montagna
Author-email: marcojoemontagna@gmail.com
License: Copyright (c) 2018 Marco Montagna
Requires-Dist: cryptography (>=2.3.0)
Requires-Dist: generic-encoders (<1.0)
